LICENSE
MANIFEST.in
README.md
requirements.txt
setup.py
emonoda/__init__.py
emonoda/cli.py
emonoda/fmt.py
emonoda/tfile.py
emonoda/tools.py
emonoda.egg-info/PKG-INFO
emonoda.egg-info/SOURCES.txt
emonoda.egg-info/dependency_links.txt
emonoda.egg-info/entry_points.txt
emonoda.egg-info/requires.txt
emonoda.egg-info/top_level.txt
emonoda/apps/__init__.py
emonoda/apps/emconfetti_demo.py
emonoda/apps/emconfetti_tghi.py
emonoda/apps/emdiff.py
emonoda/apps/emfile.py
emonoda/apps/emfind.py
emonoda/apps/emload.py
emonoda/apps/emrm.py
emonoda/apps/emstat.py
emonoda/apps/emupdate.py
emonoda/apps/hooks/__init__.py
emonoda/apps/hooks/rtorrent/__init__.py
emonoda/apps/hooks/rtorrent/collectd_stat.py
emonoda/apps/hooks/rtorrent/manage_trackers.py
emonoda/apps/hooks/transmission/__init__.py
emonoda/apps/hooks/transmission/redownload.py
emonoda/helpers/__init__.py
emonoda/helpers/datacache.py
emonoda/helpers/surprise.py
emonoda/helpers/tcollection.py
emonoda/optconf/__init__.py
emonoda/optconf/converters.py
emonoda/optconf/dumper.py
emonoda/optconf/loader.py
emonoda/plugins/__init__.py
emonoda/plugins/clients/__init__.py
emonoda/plugins/clients/ktorrent.py
emonoda/plugins/clients/qbittorrent.py
emonoda/plugins/clients/rtorrent.py
emonoda/plugins/clients/transmission.py
emonoda/plugins/confetti/__init__.py
emonoda/plugins/confetti/atom.py
emonoda/plugins/confetti/email.py
emonoda/plugins/confetti/pushover.py
emonoda/plugins/confetti/telegrem.py
emonoda/plugins/confetti/templates/atom.html.emupdate.mako
emonoda/plugins/confetti/templates/atom.plain.emupdate.mako
emonoda/plugins/confetti/templates/email.html.emupdate.mako
emonoda/plugins/confetti/templates/email.plain.emupdate.mako
emonoda/plugins/confetti/templates/pushover.emupdate.mako
emonoda/plugins/confetti/templates/telegram.emupdate.mako
emonoda/plugins/trackers/__init__.py
emonoda/plugins/trackers/booktracker_org.py
emonoda/plugins/trackers/ipv6_nnm_club_name.py
emonoda/plugins/trackers/kinozal_tv.py
emonoda/plugins/trackers/nnm_club_me.py
emonoda/plugins/trackers/pornolab_net.py
emonoda/plugins/trackers/pravtor_ru.py
emonoda/plugins/trackers/rutor_info.py
emonoda/plugins/trackers/rutracker_org.py
