Metadata-Version: 2.1
Name: emonoda
Version: 2.1.33
Summary: A set of tools to organize and manage your torrents
Home-page: https://github.com/mdevaev/emonoda
Author: Devaev Maxim
Author-email: mdevaev@gmail.com
License: GPLv3
Platform: any
Classifier: License :: OSI Approved :: GNU General Public License v3 or later (GPLv3+)
Classifier: Development Status :: 5 - Production/Stable
Classifier: Programming Language :: Python :: 3.10
Classifier: Programming Language :: Cython
Classifier: Topic :: Software Development :: Libraries :: Python Modules
Classifier: Topic :: Communications :: File Sharing
Classifier: Topic :: Internet :: WWW/HTTP
Classifier: Topic :: Utilities
Classifier: Operating System :: OS Independent
Classifier: Intended Audience :: System Administrators
Classifier: Intended Audience :: End Users/Desktop
License-File: LICENSE
